adafruit_lsm9ds0.py
adafruit_circuitpython_lsm9ds0-2.2.22.dist-info/licenses/LICENSE
adafruit_circuitpython_lsm9ds0-2.2.22.dist-info/METADATA
adafruit_circuitpython_lsm9ds0-2.2.22.dist-info/WHEEL
adafruit_circuitpython_lsm9ds0-2.2.22.dist-info/top_level.txt
adafruit_circuitpython_lsm9ds0-2.2.22.dist-info/RECORD
