Metadata-Version: 2.4
Name: adafruit-circuitpython-lsm9ds0
Version: 2.2.22
Summary: CircuitPython library for LSM9DS0 accelerometer, magnetometer, gyroscope.
Author-email: Adafruit Industries <circuitpython@adafruit.com>
License: MIT
Project-URL: Homepage, https://github.com/adafruit/Adafruit_CircuitPython_LSM9DS0
Keywords: adafruit,lsm9ds0,accelerometer,magnetometer,gyroscope,breakout,hardwaremicropython,circuitpython
Classifier: Intended Audience :: Developers
Classifier: Topic :: Software Development :: Libraries
Classifier: Topic :: Software Development :: Embedded Systems
Classifier: Topic :: System :: Hardware
Classifier: License :: OSI Approved :: MIT License
Classifier: Programming Language :: Python :: 3
License-File: LICENSE
Requires-Dist: Adafruit-Blinka
Requires-Dist: adafruit-circuitpython-busdevice
Provides-Extra: optional
Dynamic: license-file
